odoo/addons/sale_category_pricelist/README.rst
odoo/addons/sale_category_pricelist/__init__.py
odoo/addons/sale_category_pricelist/__manifest__.py
odoo/addons/sale_category_pricelist/i18n/es.po
odoo/addons/sale_category_pricelist/models/__init__.py
odoo/addons/sale_category_pricelist/models/product_pricelist_item.py
odoo/addons/sale_category_pricelist/models/product_sale_category.py
odoo/addons/sale_category_pricelist/models/product_template.py
odoo/addons/sale_category_pricelist/readme/CONFIGURE.md
odoo/addons/sale_category_pricelist/readme/CONTRIBUTORS.md
odoo/addons/sale_category_pricelist/readme/DESCRIPTION.md
odoo/addons/sale_category_pricelist/security/ir.model.access.csv
odoo/addons/sale_category_pricelist/static/description/icon.png
odoo/addons/sale_category_pricelist/static/description/index.html
odoo/addons/sale_category_pricelist/views/product_pricelist_item_views.xml
odoo/addons/sale_category_pricelist/views/product_sale_category_views.xml
odoo/addons/sale_category_pricelist/views/product_views.xml
odoo_addon_sale_category_pricelist-16.0.1.0.0.2.dist-info/METADATA
odoo_addon_sale_category_pricelist-16.0.1.0.0.2.dist-info/WHEEL
odoo_addon_sale_category_pricelist-16.0.1.0.0.2.dist-info/top_level.txt
odoo_addon_sale_category_pricelist-16.0.1.0.0.2.dist-info/RECORD
